{
  "download_base": "http://cdn233.my-card.in/",
  "version": "2016122501",
  "pre_version": "2016122801",
  "ygo233_version": "0.0.5",
  "date": "2016-12-25",
  "txt": "YGOPRO 233服 自动更新测试中。\n\n更新SD31+PP19+20AP等新卡。\n\n自动更新遇到问题请联系尸体反馈。",
  "pre_date": "2016-12-28",
  "pre_txt": "2016-12-28 01:02\n新卡：真龙剑皇 卓辉星·拼图、真龙凰的使徒、真龙的默示录。\n更新：真龙怪兽应能解放里侧表示的永续魔法·陷阱卡上级召唤。\n修复：霸王龙 扎克部分场合不能使用异色眼融合融合召唤的问题。\n2016-12-26 18:16\n更新：部分卡涉及王家长眠之谷的处理。\n修复：娱乐伙伴 U合石人无法使用的问题。\n修复：决斗者降临无法检索灵摆融合的问题。\n2016-12-26 12:49\n修复：娱乐伙伴 U合石人不能把墓地的卡加入手卡的问题，和不能使用连锁素材融合的问题。\n修复：幻影骑士团 诅咒标枪效果可以在伤害步骤伤害计算后发动的问题。\n修复：雾动机龙咆哮灵摆召唤限制只持续1回合的问题。"
}